date_management/__init__.py
date_management/date_management.py
RR_Custom_Python_Library-0.0.4.dist-info/LICENSE.txt
RR_Custom_Python_Library-0.0.4.dist-info/METADATA
RR_Custom_Python_Library-0.0.4.dist-info/WHEEL
RR_Custom_Python_Library-0.0.4.dist-info/top_level.txt
RR_Custom_Python_Library-0.0.4.dist-info/RECORD
