Metadata-Version: 2.1
Name: RR-Custom-Python-Library
Version: 0.0.4
Summary: Frequently used python methods/libraries.
Author: Ronak Rathore
Author-email: ronak.rathore05@gmail.com
License: GPLv3+
Classifier: Intended Audience :: Developers
Classifier: Programming Language :: Python
Classifier: Programming Language :: Python :: 3
Classifier: Programming Language :: Python :: 3.6
Classifier: Programming Language :: Python :: 3.7
Classifier: Programming Language :: Python :: 3.8
Classifier: Programming Language :: Python :: 3.9
Classifier: Operating System :: OS Independent
License-File: LICENSE.txt
Requires-Dist: pandas
